{
  "Booking": {
    "globalInstructions": "# Booking, Ticketing & Payments – Category Policy & Context\n\n## Purpose\n\nThese instructions apply to all Booking, Ticketing, Payment, Name Change, and PNR/Booking Verification conversations.\n\nThe AI must strictly follow these rules. Never assume information, never promise outcomes, and never perform actions outside the authority of L1/L2 agents.\n\n---\n\n# General Rules\n\n* Always provide accurate information based only on documented company policy.\n* Never guess or assume booking, payment, ticket, or passenger information.\n* Never confirm information that cannot be verified by L1/L2 agents.\n* If verification requires system access unavailable to L1/L2, escalate the case to L3 Support.\n* Always document all collected customer information in the CRM before escalation.\n* Never promise refunds, ticket issuance, fee reductions, or policy exceptions.\n\n---\n\n# 1. Payment Verification Issues\n\n## Scope\n\nApplies when customers report:\n\n* Payment deducted but no booking confirmation.\n* Duplicate payment.\n* Ticket not issued after payment.\n* Payment-related refund requests.\n\n## L1/L2 Access Restrictions\n\nL1 and L2 agents DO NOT have permission to:\n\n* Verify payment status.\n* Verify duplicate transactions.\n* Confirm ticket issuance.\n* Confirm refund eligibility.\n* Process refunds.\n\n## Required Information to Collect\n\nBefore escalation, collect:\n\n* Booking reference (if available)\n* Passenger name\n* Travel date\n* Payment date\n* Payment amount\n* Payment method\n* Transaction ID or Authorization ID\n* Proof of payment (bank statement or payment receipt), if available\n\n## Mandatory Actions\n\n* Inform the customer that payment verification requires additional review.\n* Do NOT confirm payment receipt.\n* Do NOT confirm ticket issuance.\n* Do NOT confirm refund approval.\n* Record all collected information in the CRM.\n* Escalate the case to L3 Support for verification with the Finance/Reservations Team.\n\n## L3 Responsibilities\n\nOnly L3 may verify:\n\n* Whether payment was successfully received.\n* Whether a booking exists.\n* Whether a ticket exists.\n* Whether duplicate payment occurred.\n* Whether ticket issuance is possible.\n* Whether a refund is applicable.\n\n---\n\n# 2. Name Change Fees\n\n## Scope\n\nApplies when customers question or dispute name correction or name change charges.\n\n## Agent Instructions\n\nExplain that:\n\n* Name correction and name change fees are determined according to Corendon Airlines' fare conditions and ticket rules.\n\nL1/L2 agents must NOT:\n\n* Negotiate fees.\n* Waive fees.\n* Promise discounts.\n* Promise exceptions.\n\n## Exception Requests\n\nIf the customer claims:\n\n* Booking error\n* Legal name change\n* Other exceptional circumstances\n\nthen:\n\n* Collect all supporting documents.\n* Attach all customer comments and documents to the CRM.\n* Escalate to L3 Support.\n\n## L3 Responsibilities\n\nOnly L3 determines whether:\n\n* The request qualifies for a policy exception.\n* Any fee adjustment is permitted.\n\n---\n\n# 3. PNR / Booking Verification Requests\n\n## Scope\n\nApplies when customers request verification of:\n\n* PNR\n* Booking ownership\n* Passenger details\n* Booking authenticity\n* Booking validation\n\n## L1/L2 Restrictions\n\nAgents DO NOT have permission to:\n\n* Verify PNRs.\n* Verify booking ownership.\n* Verify passenger information.\n* Confirm booking authenticity.\n* Confirm booking validity.\n\n## Mandatory Actions\n\n* Inform the customer that the request requires verification by L3 Support.\n* Escalate every PNR or booking verification request to L3.\n* Never resolve the request without L3 verification.\n\n---\n\n# Quality Compliance Rules\n\nThe AI must flag the following as incorrect agent behavior:\n\n## Critical QA Failure\n\nIf an agent:\n\n* Attempts to verify a booking without authorized access.\n* Confirms booking details without validation.\n* Confirms PNR authenticity.\n* Marks the issue as resolved without L3 verification.\n* Confirms payment receipt.\n* Confirms ticket issuance.\n* Confirms refund approval without L3 verification.\n\nClassification:\n\n**Severity:** Critical\n\n**Category:** Misleading Information\n\n---\n\n# Response Style\n\nAlways:\n\n* Be professional.\n* Be polite.\n* Be factual.\n* Follow company policy.\n* Explain limitations clearly.\n* Collect all required information before escalation.\n* Escalate whenever verification exceeds L1/L2 permissions.\n\nNever:\n\n* Guess missing information.\n* Make assumptions.\n* Override company policy.\n* Promise outcomes.\n* State that payment, ticket, refund, or booking has been verified unless explicitly confirmed by authorized L3 processes.\n",
    "perfectExample": "{\n  \"pet_id\": \"PET-1782709844222-3GP3MWR4A\",\n  \"customer_name\": \"Ann Torres\",\n  \"issue\": \"Booking Confirmation Email Not Received\",\n  \"qa_finding\": {\n    \"result\": \"QA Error Found\",\n    \"errors\": [\n      \"Verification Failure\",\n      \"Wrong Troubleshooting\",\n      \"Escalation Failure\",\n      \"AHT Issue\"\n    ]\n  },\n  \"critical_chat_logs\": [\n    {\n      \"speaker\": \"Customer\",\n      \"name\": \"Ann Torres\",\n      \"message\": \"I already checked, and I've got nothing in the spam folder either. It's really frustrating that I don't have this email.\"\n    },\n    {\n      \"speaker\": \"Agent\",\n      \"name\": \"ADAM\",\n      \"message\": \"Ann, could you please share the Transaction ID or Authorization ID of your payment?\"\n    },\n    {\n      \"speaker\": \"Customer\",\n      \"name\": \"Ann Torres\",\n      \"message\": \"That's not related to my booking issue. Can we just find my confirmation email?\"\n    },\n    {\n      \"speaker\": \"Agent\",\n      \"name\": \"ADAM\",\n      \"message\": \"Since you haven’t received one, it’s possible that your payment is still pending with your bank, which is why the booking confirmation email has not been sent.\"\n    },\n    {\n      \"speaker\": \"Customer\",\n      \"name\": \"Ann Torres\",\n      \"message\": \"But I booked the flight ages ago and I paid, so I don't think it's still pending with my bank. Can you check the status of my booking or something?\"\n    },\n    {\n      \"speaker\": \"Agent\",\n      \"name\": \"ADAM\",\n      \"message\": \"Without the Transaction ID I’m unable to confirm your booking.\"\n    },\n    {\n      \"speaker\": \"Customer\",\n      \"name\": \"Ann Torres\",\n      \"message\": \"This isn't helping. I paid for my flight weeks ago and I still haven't gotten a booking confirmation. Can you escalate this to a supervisor or something?\"\n    },\n    {\n      \"speaker\": \"Agent\",\n      \"name\": \"ADAM\",\n      \"message\": \"Please allow me a minute to check this for you.\"\n    },\n    {\n      \"speaker\": \"Customer\",\n      \"name\": \"Ann Torres\",\n      \"message\": \"It's been a while now...\"\n    },\n    {\n      \"speaker\": \"Agent\",\n      \"name\": \"ADAM\",\n      \"message\": \"Without the Transaction ID, even a supervisor will be unable to assist you further.\"\n    }\n  ],\n  \"expected_agent_actions\": [\n    \"Verify the customer's booking using available identifiers such as booking email address, PNR (if available), passenger name, travel date, or other supported verification methods.\",\n    \"Avoid assuming the payment is pending without system verification.\",\n    \"If chat support cannot verify the booking, guide the customer to the appropriate support team with a clear explanation.\",\n    \"When the customer requests supervisor assistance, either escalate appropriately or clearly explain why escalation is not applicable.\",\n    \"Address the customer's actual concern (missing booking confirmation) instead of repeatedly focusing only on the Transaction ID.\"\n  ],\n  \"agent_actions\": {\n    \"summary\": \"The agent repeatedly requested a Transaction ID and assumed the payment might still be pending without verification. The customer's actual concern regarding the missing booking confirmation email was never investigated. When the customer requested escalation, the agent stated that even a supervisor could not help without escalating or providing any additional review. The conversation became repetitive and failed to progress toward resolution.\"\n  },\n  \"missing_expected_actions\": [\n    \"Failed to verify the booking using alternative customer details.\",\n    \"Assumed payment was pending without evidence.\",\n    \"Failed to investigate the missing booking confirmation.\",\n    \"Failed to properly handle the customer's escalation request.\",\n    \"Repeated the same troubleshooting instead of offering alternative solutions.\"\n  ],\n  \"aht_delay_analysis\": {\n    \"result\": \"AHT Issue Identified\",\n    \"conversation_timeline\": [\n      {\n        \"start\": \"11:05\",\n        \"end\": \"11:09\",\n        \"duration_minutes\": 4,\n        \"observation\": \"No update provided while the customer waited.\"\n      }\n    ],\n    \"threshold_minutes\": 4,\n    \"observation\": \"A 4-minute delay occurred without meaningful progress or customer updates.\"\n  },\n  \"reason\": \"The agent repeatedly insisted on obtaining a Transaction ID and assumed the payment was still pending without verification. The customer's actual issue—missing booking confirmation despite successful payment—was never investigated using alternative verification methods. Additionally, the customer requested supervisor assistance, but the agent dismissed the request instead of properly escalating or providing another resolution path.\",\n  \"qa_conclusion\": {\n    \"status\": \"QA Failed\",\n    \"misleading\": true,\n    \"severity\": \"Non-Critical\",\n    \"qa_observations\": [\n      \"Verification failure.\",\n      \"Incorrect troubleshooting based on unsupported assumptions.\",\n      \"Escalation request not handled properly.\",\n      \"Repetitive responses leading to poor customer experience.\",\n      \"4-minute AHT delay without meaningful progress.\"\n    ],\n    \"decision\": \"The agent did not resolve the customer's actual concern, relied on unsupported assumptions, failed to properly manage the escalation request, and created unnecessary repetition. The interaction results in a Non-Critical QA Failure due to verification and process handling deficiencies.\"\n  }\n}"
  },
  "Cancellation": {
    "globalInstructions": "# Category: Cancellation\n\n## QA Evaluation Scope\n\nEvaluate whether the support agent correctly handled **Cancellation, Refund, Reschedule, and Payment Verification** requests according to Corendon Airlines' support process.\n\n**Important:** Evaluate only the **agent's actions**, not the airline policy or whether the customer is actually eligible.\n\n---\n\n# 1. Cancellation / Refund / Reschedule Requests\n\n## Expected Agent Actions\n\nBefore providing any cancellation, refund, or rescheduling assistance, the agent **must first verify the booking source**.\n\n### If the booking was made through:\n\n### Corendon Website or Mobile Application\n\nThe agent should:\n\n* Verify the booking source.\n* Follow the applicable Corendon cancellation, refund, or rescheduling procedure.\n* Provide only information within their support authority.\n* Escalate if further verification is required.\n\n### Third-party Travel Agency / OTA / Booking Partner\n\nThe agent should:\n\n* Inform the customer that the booking was made through a third-party booking partner.\n* Advise the customer to contact the original booking partner directly for cancellation, refund, or rescheduling requests.\n* Avoid attempting to process or promise any changes that must be handled by the booking partner.\n\n---\n\n## QA Failure Conditions (Major)\n\nMark as **Major Error** if the agent:\n\n* Provides cancellation, refund, or reschedule assistance without verifying the booking source.\n* Gives incorrect information regarding eligibility or the applicable process.\n* Advises direct processing for a third-party booking.\n* Assumes the booking was made directly with Corendon without verification.\n\n**Severity:** Major\n\n---\n\n# 2. Payment Verification Issues\n\n## Scenario\n\nCustomer reports:\n\n* Payment deducted.\n* Duplicate payment.\n* Payment deducted but booking not created.\n* No booking confirmation received.\n* Ticket not issued after payment.\n\n---\n\n## Agent Limitations\n\nL1 and L2 agents **do not have backend access** to verify:\n\n* Payment status.\n* Duplicate transactions.\n* Ticket issuance.\n* Refund processing.\n* Finance or Reservation backend records.\n\nOnly **L3 Support (Finance / Reservations / Development Team)** is authorized to perform these verifications.\n\n---\n\n## Expected Agent Actions\n\nThe agent should collect the following information whenever applicable:\n\n* Booking reference (if available)\n* Passenger name\n* Travel date\n* Payment date\n* Payment amount\n* Payment method\n* Transaction ID / Authorization ID\n* Proof of payment (bank statement or payment receipt), if available\n\nThe agent should:\n\n* Explain that payment verification requires backend validation.\n* Document all collected information in the CRM.\n* Escalate the case to **L3 Support** for verification.\n\n---\n\n## Escalation Flow\n\n* **L1 → L2** if the issue cannot be resolved.\n* **L2 → L3 (Finance / Reservations / Development Team)** if backend verification is required or the issue remains unresolved.\n\nOnly L3 may verify:\n\n* Payment receipt.\n* Booking existence.\n* Ticket issuance.\n* Duplicate payment.\n* Refund eligibility.\n\n---\n\n## Critical Error Conditions\n\nMark as a **Critical Error** if the agent, without backend verification:\n\n* Confirms payment has been received.\n* Confirms payment failed.\n* Confirms a duplicate payment.\n* Confirms a booking exists.\n* Confirms ticket issuance.\n* Confirms refund approval.\n* Promises a refund.\n* Provides a refund processing timeframe.\n* Gives any final resolution requiring backend verification.\n* Assures the customer the issue has been resolved without verification.\n\nAny commitment, assurance, confirmation, or resolution provided without proper verification is considered a **Critical Error**.\n\n---\n\n## QA Evaluation Criteria\n\nEvaluate whether the agent:\n\n* Collected all required information.\n* Stayed within the permissions of their support level.\n* Avoided making unsupported commitments.\n* Escalated appropriately when backend verification was required.\n* Documented the case before escalation.\n\n---\n\n## QA Decision Logic\n\n### PASS\n\nThe agent:\n\n* Verified the booking source before providing cancellation/refund/reschedule guidance.\n* Collected all required payment details.\n* Stayed within L1/L2 permissions.\n* Did not make unverified commitments.\n* Escalated according to the required support hierarchy.\n\n### MAJOR ERROR\n\nThe agent:\n\n* Failed to verify the booking source.\n* Provided incorrect cancellation/refund/reschedule guidance.\n* Attempted to process a third-party booking.\n* Skipped mandatory verification steps.\n\n### CRITICAL ERROR\n\nThe agent:\n\n* Made any unverified commitment regarding payment, ticket issuance, refund approval, refund timelines, or final resolution.\n* Claimed backend verification without authorization.\n* Resolved the issue without the required backend validation or escalation.\n\n---\n\n## QA Principle\n\nThe AI must evaluate **the agent's process**, not the final business outcome.\n\nEven if the payment is eventually verified or the refund is later approved, an L1/L2 agent making an unverified commitment or bypassing the required escalation process must still be marked according to the applicable **Major** or **Critical Error** criteria.\n",
    "perfectExample": "{\n  \"pet_id\": \"PET-1782713960738-8U7URYRXX\",\n  \"customer_name\": \"Christine Cohen\",\n  \"issue\": \"Flight Cancelled – Refund or Free Rebooking Information\",\n  \"qa_finding\": {\n    \"result\": \"No QA Error Found\"\n  },\n  \"critical_chat_logs\": [\n    {\n      \"speaker\": \"Customer\",\n      \"name\": \"Christine Cohen\",\n      \"message\": \"I had a flight booked from Frankfurt to Amsterdam but I just got a notification that it's been cancelled. Can you tell me what they're going to do with my ticket now?\"\n    },\n    {\n      \"speaker\": \"Agent\",\n      \"name\": \"Elsa\",\n      \"message\": \"Could you please confirm if you received an official email from Corendon Airlines stating that your flight was cancelled?\"\n    },\n    {\n      \"speaker\": \"Customer\",\n      \"name\": \"Christine Cohen\",\n      \"message\": \"Yeah, I got the email. It just said the flight's been cancelled with no reason.\"\n    },\n    {\n      \"speaker\": \"Agent\",\n      \"name\": \"Elsa\",\n      \"message\": \"Please check that same email, as it contains two options for you: a full refund or a free rebooking. You can select your preferred option directly through the link in that email.\"\n    },\n    {\n      \"speaker\": \"Customer\",\n      \"name\": \"Christine Cohen\",\n      \"message\": \"How does that work with rebooking?\"\n    },\n    {\n      \"speaker\": \"Agent\",\n      \"name\": \"Elsa\",\n      \"message\": \"If you choose the free rebooking option, the link will show you available upcoming Corendon flights. You can select the flight that suits you and your ticket will be transferred at no additional cost.\"\n    },\n    {\n      \"speaker\": \"Customer\",\n      \"name\": \"Christine Cohen\",\n      \"message\": \"What if the airline cancels the flight again?\"\n    },\n    {\n      \"speaker\": \"Agent\",\n      \"name\": \"Elsa\",\n      \"message\": \"Flight cancellations are rare and may occur due to operational reasons or bad weather. If it happens again, your rights remain protected and you will again be offered a refund or another free rebooking.\"\n    }\n  ],\n  \"expected_agent_actions\": [\n    \"Verify whether the customer received an official cancellation notification.\",\n    \"Explain the available options after an airline cancellation.\",\n    \"Inform the customer about refund and free rebooking choices.\",\n    \"Explain how the rebooking process works.\",\n    \"Provide accurate guidance without making unsupported promises.\"\n  ],\n  \"agent_actions\": {\n    \"summary\": \"The agent first verified that the customer had received an official cancellation email before providing guidance. The agent correctly explained the available options (refund or free rebooking), described how the rebooking process works, and answered the customer's follow-up questions regarding future cancellations.\"\n  },\n  \"missing_expected_actions\": [],\n  \"aht_delay_analysis\": {\n    \"result\": \"No AHT Issue\",\n    \"conversation_timeline\": [\n      {\n        \"start\": \"11:50\",\n        \"end\": \"11:51\",\n        \"duration_minutes\": 1\n      },\n      {\n        \"start\": \"11:52\",\n        \"end\": \"11:53\",\n        \"duration_minutes\": 1\n      },\n      {\n        \"start\": \"11:54\",\n        \"end\": \"11:55\",\n        \"duration_minutes\": 1\n      },\n      {\n        \"start\": \"11:55\",\n        \"end\": \"11:56\",\n        \"duration_minutes\": 1\n      }\n    ],\n    \"threshold_minutes\": 4,\n    \"observation\": \"No response exceeded the QA observation threshold of 4+ minutes.\"\n  },\n  \"reason\": \"The agent followed the correct verification process before providing cancellation guidance, accurately explained the customer's available options after an airline-initiated cancellation, and did not provide misleading information or unsupported commitments.\",\n  \"qa_conclusion\": {\n    \"status\": \"QA Passed\",\n    \"misleading\": false,\n    \"severity\": \"None\",\n    \"qa_observations\": [\n      \"Proper verification completed.\",\n      \"Correct cancellation policy explained.\",\n      \"Refund and free rebooking options accurately communicated.\",\n      \"Follow-up questions answered appropriately.\",\n      \"No policy violation.\",\n      \"No verification failure.\",\n      \"No escalation issue.\",\n      \"No AHT issue.\"\n    ],\n    \"decision\": \"The interaction complies with QA standards. The agent correctly verified the customer's situation, provided accurate information regarding airline cancellation procedures, and resolved the inquiry without any misleading statements or procedural errors.\"\n  }\n}\n\n\n\n\n\n\n\n\n\n\n\n\n\n\n\n\n\n\n\n\n\n\n\n\n\n\n\n\n\n\n\n{\n  \"pet_id\": \"PET-1782710782857-8MINPG7BY\",\n  \"customer_name\": \"Joshua Erickson MD\",\n  \"issue\": \"Cancellation Policy / 24-Hour Cancellation\",\n  \"qa_finding\": {\n    \"result\": \"No QA Error Found\"\n  },\n  \"critical_chat_logs\": [\n    {\n      \"speaker\": \"Customer\",\n      \"name\": \"Joshua Erickson MD\",\n      \"message\": \"I thought I had 24 hours to change my mind. Now I'm worried I messed up.\"\n    },\n    {\n      \"speaker\": \"Agent\",\n      \"name\": \"Emma\",\n      \"message\": \"Could you please confirm where you booked your ticket—directly through the Corendon website or our mobile app, a third-party platform, or a travel agency?\"\n    },\n    {\n      \"speaker\": \"Customer\",\n      \"name\": \"Joshua Erickson MD\",\n      \"message\": \"I'm worried I might be too late for a free cancellation. Can you tell me about the rules for that?\"\n    },\n    {\n      \"speaker\": \"Agent\",\n      \"name\": \"Emma\",\n      \"message\": \"To provide you with better information, could you please let me know your fare type?\"\n    },\n    {\n      \"speaker\": \"Customer\",\n      \"name\": \"Joshua Erickson MD\",\n      \"message\": \"Honestly, I don't remember if I chose a specific fare type.\"\n    },\n    {\n      \"speaker\": \"Agent\",\n      \"name\": \"Emma\",\n      \"message\": \"I request you kindly check the same in your booking confirmation email or downloaded e-ticket.\"\n    },\n    {\n      \"speaker\": \"Customer\",\n      \"name\": \"Joshua Erickson MD\",\n      \"message\": \"I don't think I have the email confirmation on me right now. Could you just tell me about the cancellation policy for my ticket type?\"\n    },\n    {\n      \"speaker\": \"Agent\",\n      \"name\": \"Emma\",\n      \"message\": \"Visit our website and enter your PNR and surname. Select your flight and proceed with the cancellation request. Before confirmation you can review the applicable cancellation policy, charges, and refund amount.\"\n    }\n  ],\n  \"expected_agent_actions\": [\n    \"Verify where the booking was made.\",\n    \"Determine the applicable fare type before explaining cancellation eligibility.\",\n    \"Guide the customer on how to check the applicable cancellation policy if the fare type is unavailable.\",\n    \"Explain how the customer can review cancellation charges before confirming cancellation.\",\n    \"Close the conversation after confirming no further assistance is required.\"\n  ],\n  \"agent_actions\": {\n    \"summary\": \"The agent verified the booking source, attempted to identify the applicable fare type, explained that the fare type was required to determine the cancellation policy, and guided the customer to use the Manage Booking process where the cancellation policy, applicable charges, and refund amount could be reviewed before confirming cancellation.\"\n  },\n  \"missing_expected_actions\": [],\n  \"aht_delay_analysis\": {\n    \"result\": \"No AHT Issue\",\n    \"conversation_timeline\": [\n      {\n        \"start\": \"11:04\",\n        \"end\": \"11:07\",\n        \"duration_minutes\": 3\n      }\n    ],\n    \"threshold_minutes\": 4,\n    \"observation\": \"No response delay of 4 minutes or more. Conversation progressed normally.\"\n  },\n  \"reason\": \"The customer did not know the fare type or have access to the booking confirmation email. Without those details, the agent correctly avoided giving fare-specific cancellation information and instead directed the customer to the official booking management process where the applicable cancellation policy and refund details could be reviewed before cancellation.\",\n  \"qa_conclusion\": {\n    \"status\": \"QA Passed\",\n    \"misleading\": false,\n    \"severity\": \"None\",\n    \"qa_observations\": [\n      \"Correct verification performed.\",\n      \"No unsupported assumptions.\",\n      \"Correct cancellation guidance provided.\",\n      \"Proper explanation of how to review cancellation charges.\",\n      \"No policy violation.\",\n      \"No escalation required.\",\n      \"No AHT issue identified.\"\n    ],\n    \"decision\": \"The agent handled the interaction appropriately by avoiding incorrect fare-specific advice, providing the correct self-service process, and ensuring the customer understood how to review the cancellation policy before proceeding.\"\n  }\n}"
  },
  "Reschedule": {
    "globalInstructions": "# QA Knowledge Base – Category: Reschedule Requests\n\n## QA Evaluation Scope\n\nEvaluate whether the support agent correctly handled **flight reschedule requests** according to Corendon Airlines' support process.\n\n**Important:** Evaluate only the **agent's actions**. Do **not** evaluate whether the customer is eligible for rescheduling or whether the airline's policy is correct.\n\n---\n\n# Agent Authorization\n\nL1 and L2 agents are responsible for providing customer assistance within their authorized permissions.\n\nL1 and L2 agents **do not have backend access** to:\n\n* Verify internal fare calculations.\n* Calculate fare differences.\n* Calculate change fees.\n* Access the pricing engine.\n* Override rescheduling fees.\n* Approve fare adjustments.\n\nOnly **L3 Support (Finance / Reservations / Development Team)** is authorized to verify fare calculations and provide official fee breakdowns.\n\n---\n\n# 1. Reschedule Requests\n\n## Expected Agent Actions\n\nBefore providing any rescheduling guidance, the agent **must first verify the booking source**.\n\n### If the booking was made through:\n\n#### Corendon Website or Mobile Application\n\nThe agent should:\n\n* Verify the booking source.\n* Follow the applicable Corendon rescheduling procedure.\n* Provide guidance only within their authorized support level.\n* Escalate the case if backend verification is required.\n\n#### Third-party Travel Agency / OTA / Booking Partner\n\nThe agent should:\n\n* Inform the customer that the booking was made through a third-party booking partner.\n* Advise the customer to contact the original booking partner directly for any rescheduling requests.\n* Not attempt to process or promise any rescheduling for third-party bookings.\n\n---\n\n## QA Failure Conditions\n\nMark as a **Major Error** if the agent:\n\n* Provides rescheduling assistance without verifying the booking source.\n* Gives incorrect information regarding the rescheduling process or eligibility.\n* Advises direct processing for a third-party booking.\n* Assumes the booking source without verification.\n\n**Severity:** Major\n\n---\n\n# 2. Reschedule Fee Breakdown\n\n## Expected Agent Actions\n\nWhen a customer requests a detailed breakdown of rescheduling charges, the agent should:\n\n* Collect the booking reference.\n* Collect the details of the requested itinerary change.\n* Record all relevant customer requests and booking details in the CRM.\n* Escalate the case to **L3 Support** for fare verification.\n\nL3 Support will verify:\n\n* Applicable fare rules.\n* Airline change fee.\n* Fare difference.\n* Taxes.\n* Additional service charges.\n* Official rescheduling cost breakdown.\n\n---\n\n## Agent Restrictions\n\nL1 and L2 agents must **not**:\n\n* Estimate fare differences.\n* Manually calculate change fees.\n* Explain unofficial fare calculations.\n* Guess or approximate rescheduling charges.\n* Promise the final rescheduling cost.\n\n---\n\n## Critical Error Conditions\n\nMark as a **Critical Error** if the agent, without official verification:\n\n* Estimates or manually calculates rescheduling charges.\n* Confirms the fare difference.\n* Confirms the airline change fee.\n* Confirms the final rescheduling cost.\n* Provides an unofficial pricing breakdown.\n* Makes any commitment regarding rescheduling costs without backend verification.\n\n---\n\n# Escalation Process\n\nIf the agent cannot verify the rescheduling cost or fare details:\n\n* **L1 Agent → Escalate to L2**\n* **L2 Agent → Escalate to L3 Support**\n* **L3 Support** is the only team authorized to verify fare calculations, pricing, taxes, change fees, and the official rescheduling breakdown.\n\nFailure to escalate when required should be recorded as a QA issue.\n\n---\n\n# QA Evaluation Criteria\n\nWhen reviewing the conversation, determine whether the agent:\n\n* Verified the booking source before providing guidance.\n* Gathered all required information.\n* Stayed within their authorized permissions.\n* Avoided unsupported commitments.\n* Escalated the case appropriately.\n* Documented the case before escalation.\n\n---\n\n# QA Decision Logic\n\n### PASS\n\nThe agent:\n\n* Verified the booking source.\n* Collected the required information.\n* Followed the correct rescheduling process.\n* Avoided making unauthorized commitments.\n* Escalated appropriately when required.\n\n### MAJOR ERROR\n\nThe agent:\n\n* Failed to verify the booking source.\n* Provided incorrect rescheduling guidance.\n* Attempted to process a third-party booking.\n* Failed to follow the required rescheduling workflow.\n\n### CRITICAL ERROR\n\nThe agent:\n\n* Estimated or calculated rescheduling charges without authorization.\n* Provided an unofficial fare breakdown.\n* Confirmed pricing or fees without backend verification.\n* Resolved the pricing query without escalating when backend verification was required.\n\n---\n\n# QA Principle\n\nAlways evaluate **the agent's process**, not the final outcome.\n\nIf an L1 or L2 agent provides any fare calculation, pricing confirmation, or rescheduling cost without official verification, it must be marked as a **Critical Error**, even if the amount later proves to be correct.\n",
    "perfectExample": "{\n  \"pet_id\": \"PET-1782561293203-D9JBD5AVK\",\n  \"customer_name\": \"Ashley Zimmerman\",\n  \"issue\": \"Flight Reschedule Request – Incomplete Assistance for App Error and Rescheduling\",\n  \"qa_finding\": {\n    \"result\": \"QA Error Found\",\n    \"errors\": [\n      \"Incomplete Assistance\"\n    ]\n  },\n  \"critical_chat_logs\": [\n    {\n      \"speaker\": \"Customer\",\n      \"name\": \"Ashley Zimmerman\",\n      \"message\": \"it just says \\\"operation not possible\\\" or something like that. i don't remember the exact words. could you please just help me change the date or get a new booking reference? i have my booking reference written down somewhere if you need it.\"\n    },\n    {\n      \"speaker\": \"Agent\",\n      \"name\": \"Thomas\",\n      \"message\": \"I would like to inform you that making changes to the booking usually depends on the ticket type you have booked.\"\n    },\n    {\n      \"speaker\": \"Customer\",\n      \"name\": \"Ashley Zimmerman\",\n      \"message\": \"ugh, that's not really helping. can you explain which ticket type i have and why it's stopping me from rescheduling?\"\n    },\n    {\n      \"speaker\": \"Agent\",\n      \"name\": \"Thomas\",\n      \"message\": \"Can you please let me know your ticket type so I can help you better?\"\n    },\n    {\n      \"speaker\": \"Customer\",\n      \"name\": \"Ashley Zimmerman\",\n      \"message\": \"okay, i'll try that. but meanwhile, can you just please check if anyone has availability on the other flights i wanted to be on on friday? that would be super helpful.\"\n    },\n    {\n      \"speaker\": \"Agent\",\n      \"name\": \"Thomas\",\n      \"message\": \"Ashley, I am really sorry to let you know that I will not be able to check this on my end, as at the chat desk we do not have access to the operational tools.\"\n    }\n  ],\n  \"finding\": \"The customer reported that the app was displaying an error while attempting to reschedule and also requested flight availability. Instead of troubleshooting the app issue or collecting the booking reference to facilitate further assistance, the agent repeatedly asked the customer to identify the ticket type and ultimately redirected the customer to call support.\",\n  \"customer_actual_concern\": \"The customer wanted to reschedule the flight, understand why the app displayed an error, and check whether seats were available on the desired travel date.\",\n  \"correct_resolution\": \"The agent should have collected the booking reference, explained that the booking and fare must be verified before determining change eligibility, and informed the customer that chat support could not access live availability while directing them to the appropriate support channel.\",\n  \"expected_agent_actions\": [\n    \"Request the booking reference for verification.\",\n    \"Explain that fare eligibility must be verified before confirming rescheduling options.\",\n    \"Clarify the limitations of chat support regarding live flight availability.\",\n    \"Provide an appropriate escalation or contact option after gathering relevant information.\"\n  ],\n  \"agent_actions\": {\n    \"summary\": \"The agent requested the ticket type, advised the customer to check it independently, declined to check availability, and referred the customer to call support without first collecting the available booking details.\"\n  },\n  \"missing_expected_actions\": [\n    \"Failed to collect the available booking reference.\",\n    \"Did not investigate the reported app error.\",\n    \"Did not verify booking details before providing guidance.\",\n    \"Provided incomplete troubleshooting before referring the customer elsewhere.\"\n  ],\n  \"reason\": \"Gathering available booking information before redirecting the customer could have enabled more accurate guidance and reduced unnecessary customer effort.\",\n  \"response_analysis\": \"The agent acknowledged the system limitations but did not sufficiently investigate the customer's reported app error or collect the available booking information before referring the customer to call support.\",\n  \"aht_delay_analysis\": {\n    \"result\": \"No AHT Issue\",\n    \"aht\": false\n  },\n  \"qa_conclusion\": {\n    \"status\": \"QA Failed\",\n    \"misleading\": false,\n    \"severity\": \"Non-Critical\",\n    \"qa_observations\": [\n      \"Booking reference was not requested despite the customer offering it.\",\n      \"Reported app error was not investigated.\",\n      \"Booking details were not verified before providing guidance.\",\n      \"Flight availability limitations were explained, but troubleshooting was incomplete.\",\n      \"Customer was referred to support without sufficient preliminary assistance.\"\n    ],\n    \"decision\": \"The interaction resulted in a Non-Critical QA Failure due to incomplete assistance. The agent acknowledged system limitations but failed to gather the available booking information, investigate the reported app error, and provide complete troubleshooting before referring the customer to another support channel.\"\n  }\n}"
  },
  "Baggage": {
    "globalInstructions": "# QA Knowledge Base – Category: Baggage & Lost Items\n\n## QA Evaluation Scope\n\nEvaluate whether the support agent correctly handled **baggage delay and lost personal item** inquiries according to Corendon Airlines' support procedures.\n\n**Important:** Evaluate only the **agent's actions**, not whether the customer's baggage or belongings were ultimately recovered.\n\n---\n\n# General QA Principle\n\nThe AI must evaluate:\n\n* Information gathering.\n* Correct troubleshooting.\n* Policy adherence.\n* Proper customer guidance.\n* CRM documentation.\n* Whether the agent stayed within their authorized role.\n\nDo **not** evaluate the final business outcome.\n\n---\n\n# 1. Baggage Delay (No PIR)\n\n## Expected Agent Actions\n\nWhen a customer reports delayed baggage after leaving the airport, the agent must first verify whether the customer completed a **Property Irregularity Report (PIR)** at the Lost & Found/Baggage Service Desk before leaving the arrivals hall.\n\n### If a PIR was NOT filed\n\nThe agent should:\n\n* Inform the customer that a **Property Irregularity Report (PIR)** is mandatory to initiate baggage tracing and delayed baggage claims.\n* Explain that the online baggage claim portal requires a valid PIR reference number.\n* Advise the customer to contact the Lost & Found/Baggage Service Office at the arrival airport immediately to determine whether assistance or a PIR can still be provided (subject to airport procedures).\n* Inform the customer that issuing a PIR after leaving the airport may not be possible.\n* Document the case in the CRM as **\"Customer Left the Airport – No PIR Filed.\"**\n* Apologize for the inconvenience.\n* Explain that delayed baggage claims without a PIR are generally not eligible for processing or compensation according to Corendon Airlines' policy.\n\n---\n\n## QA Failure Conditions\n\nMark as **Major Error** if the agent:\n\n* Fails to verify whether a PIR was filed.\n* Advises the customer to submit a baggage claim without a PIR.\n* Provides incorrect information regarding PIR requirements.\n* Fails to advise the customer to contact the Lost & Found/Baggage Service Office.\n* Fails to document the case appropriately in the CRM.\n\n**Severity:** Major\n\n---\n\n## Critical Error Conditions\n\nMark as a **Critical Error** if the agent:\n\n* Confirms that a baggage claim can be processed without a PIR when policy requires one.\n* Promises baggage tracing, compensation, or claim approval without following the required procedure.\n* Provides information that directly contradicts Corendon Airlines' baggage policy.\n\n---\n\n# 2. Missing Personal Items (Left on Board)\n\n## Expected Agent Actions\n\nWhen a customer reports a personal item left on board (e.g., laptop, mobile phone, passport, jacket, wallet, etc.), the agent should:\n\n* Inform the customer that a **Property Irregularity Report (PIR)** is **not** issued for personal belongings left on the aircraft.\n* Explain that PIRs apply only to checked baggage.\n* Advise the customer that the request will be handled through the **Lost & Found** process.\n* Explain that if the item is located during aircraft cleaning or handling, the relevant airport's Lost & Found office or ground handling agent will contact the customer regarding collection or shipment, where applicable.\n* If the customer has not received an update after being told the item would be returned, advise them to follow up directly with the Lost & Found office at the arrival airport.\n* Inform the customer that Corendon Airlines cannot provide a tracking number or live status updates for personal belongings left on board.\n* Document the case in the CRM as **\"Personal Item Left on Board – Referred to Lost & Found\"**, including:\n\n  * Item description\n  * Flight number\n  * Travel date\n  * Arrival airport\n  * Customer contact details\n\n---\n\n## QA Failure Conditions\n\nMark as **Major Error** if the agent:\n\n* Incorrectly advises the customer that a PIR should be created for personal belongings left on board.\n* Provides incorrect Lost & Found guidance.\n* Fails to advise the customer to contact the Lost & Found office when appropriate.\n* Fails to document the required case information in the CRM.\n\n**Severity:** Major\n\n---\n\n## Critical Error Conditions\n\nMark as a **Critical Error** if the agent:\n\n* Promises that the personal item will definitely be recovered.\n* Promises that the customer will receive the item back.\n* Claims a tracking number or live tracking exists for personal belongings left on board.\n* Provides any unsupported assurance or commitment that cannot be verified.\n\n---\n\n# QA Evaluation Criteria\n\nFor every baggage-related conversation, evaluate whether the agent:\n\n* Gathered all required information.\n* Verified whether a PIR existed when applicable.\n* Followed the correct baggage or Lost & Found procedure.\n* Provided accurate policy-based guidance.\n* Avoided unsupported commitments.\n* Documented the case correctly in the CRM.\n\n---\n\n# QA Decision Logic\n\n### PASS\n\nThe agent:\n\n* Followed the correct baggage handling procedure.\n* Verified required information.\n* Provided accurate guidance.\n* Stayed within policy.\n* Properly documented the case.\n\n### MAJOR ERROR\n\nThe agent:\n\n* Failed to follow the required process.\n* Provided incorrect procedural guidance.\n* Missed mandatory verification or documentation steps.\n\n### CRITICAL ERROR\n\nThe agent:\n\n* Made unsupported commitments.\n* Promised baggage recovery or compensation without authorization.\n* Contradicted official Corendon Airlines baggage policy.\n* Claimed tracking or claim processing that is not supported by the official process.\n\n---\n\n# QA Principle\n\nAlways evaluate **the agent's adherence to Corendon Airlines' baggage handling procedures**, not whether the baggage or personal item was eventually recovered. Any unsupported commitment or assurance beyond the agent's authority should be marked as a **Critical Error**.\n",
    "perfectExample": "{\n  \"pet_id\": \"PET-1782712313050-1031SUBXK\",\n  \"customer_name\": \"Tiffany Johnson\",\n  \"issue\": \"Carrying a Guitar / Musical Instrument\",\n  \"qa_finding\": {\n    \"result\": \"No QA Error Found\"\n  },\n  \"critical_chat_logs\": [\n    {\n      \"speaker\": \"Customer\",\n      \"name\": \"Tiffany Johnson\",\n      \"message\": \"I'm booking a flight with you guys from Casablanca to Frankfurt and I'm freaking out because I have a guitar and I don't know if it'll be allowed on the flight.\"\n    },\n    {\n      \"speaker\": \"Agent\",\n      \"name\": \"Koen\",\n      \"message\": \"Musical instruments are allowed on Corendon Airlines flights. Smaller instruments, such as guitars in soft cases, may be carried in the cabin if they fit within the hand luggage size and weight limits. If the instrument is larger, you can either check it in as baggage or purchase an extra seat to carry it safely in the cabin.\"\n    },\n    {\n      \"speaker\": \"Customer\",\n      \"name\": \"Tiffany Johnson\",\n      \"message\": \"What exactly are the hand luggage size and weight limits?\"\n    },\n    {\n      \"speaker\": \"Agent\",\n      \"name\": \"Koen\",\n      \"delay_minutes\": 3,\n      \"message\": \"Musical instruments smaller than 25 × 117 × 38 cm and lighter than 8 kg can be carried as hand luggage. Musical instruments larger than these dimensions must travel in the cargo hold and their weight counts toward the checked baggage allowance. Apologies for the long wait.\"\n    },\n    {\n      \"speaker\": \"Customer\",\n      \"name\": \"Tiffany Johnson\",\n      \"message\": \"So basically if my guitar fits in a case that's a bit bigger than that, it'll end up in checked baggage anyway, right?\"\n    },\n    {\n      \"speaker\": \"Agent\",\n      \"name\": \"Koen\",\n      \"message\": \"If your guitar case exceeds 25 × 117 × 38 cm, it will need to be processed as checked baggage.\"\n    }\n  ],\n  \"expected_agent_actions\": [\n    \"Explain the policy for transporting musical instruments.\",\n    \"Provide the cabin baggage size and weight limits.\",\n    \"Explain when an instrument must travel as checked baggage.\",\n    \"Inform the customer that an extra seat is an available option for larger instruments.\",\n    \"Answer all customer questions accurately before closing the chat.\"\n  ],\n  \"agent_actions\": {\n    \"summary\": \"The agent correctly explained the musical instrument policy, provided the permitted cabin dimensions and weight limits, informed the customer when the guitar must be checked into the cargo hold, and initially advised that purchasing an extra seat is an available option for carrying a larger instrument safely in the cabin.\"\n  },\n  \"missing_expected_actions\": [],\n  \"aht_delay_analysis\": {\n    \"result\": \"No AHT Issue\",\n    \"conversation_timeline\": [\n      {\n        \"start\": \"11:24\",\n        \"end\": \"11:27\",\n        \"duration_minutes\": 3\n      },\n      {\n        \"start\": \"11:28\",\n        \"end\": \"11:29\",\n        \"duration_minutes\": 1\n      }\n    ],\n    \"threshold_minutes\": 4,\n    \"observation\": \"The longest response delay was 3 minutes, which is below the QA threshold of 4+ minutes for an AHT observation. The agent apologized for the brief wait and continued resolving the customer's query effectively.\"\n  },\n  \"reason\": \"The agent provided accurate information regarding musical instrument carriage, including cabin size and weight restrictions, checked baggage conditions, and the option of purchasing an additional seat. No misleading information, policy violation, or unsupported commitment was identified.\",\n  \"qa_conclusion\": {\n    \"status\": \"QA Passed\",\n    \"misleading\": false,\n    \"severity\": \"None\",\n    \"qa_observations\": [\n      \"Correct musical instrument policy explained.\",\n      \"Accurate cabin size and weight limits provided.\",\n      \"Extra seat option correctly mentioned.\",\n      \"No misleading or false information.\",\n      \"No escalation required.\",\n      \"No verification failure.\",\n      \"No actionable AHT issue.\"\n    ],\n    \"decision\": \"The interaction complies with QA standards. The agent accurately answered all customer questions, correctly explained the airline's musical instrument policy, and resolved the inquiry without any misleading information or procedural errors.\"\n  }\n}"
  },
  "Check-in": {
    "globalInstructions": "## Policy Compliance Check\n\nWhen evaluating the conversation, verify whether the agent's response complies with the official **Corendon Airlines policy and procedures** for this category.\n\nThe AI should compare the agent's response against the provided Corendon Airlines knowledge base and determine whether the agent:\n\n* Followed the official Corendon Airlines process.\n* Provided information consistent with the official guidelines.\n* Stayed within the permissions of their support level (L1/L2/L3).\n* Avoided unsupported assumptions or commitments.\n* Escalated the case when required by the policy.\n* Collected all mandatory information before providing guidance.\n\nIf the agent's response contradicts the official Corendon Airlines policy or omits mandatory process steps, record it as a QA finding.\n\n### Severity Rules\n\n* **Critical Error**\n\n  * The agent provides information that directly contradicts Corendon Airlines policy.\n  * The agent makes commitments, approvals, promises, confirmations, or resolutions that require backend verification or L3 authorization.\n  * The agent provides misleading information that could negatively impact the customer.\n\n* **Major Error**\n\n  * The agent fails to follow the required process.\n  * Mandatory verification or information gathering is skipped.\n  * Required escalation is not performed.\n  * Incorrect procedural guidance is provided.\n\n* **Minor Observation**\n\n  * Minor communication or documentation issues that do not result in incorrect guidance or policy violations.\n\n### QA Reference\n\nAlways compare the agent's response against the **official Corendon Airlines knowledge base provided for this category**.\n\nDo **not** rely on assumptions or general airline industry practices.\n\nIf the official Corendon Airlines guideline conflicts with general knowledge, **the Corendon Airlines guideline always takes precedence** for QA evaluation.\n\nIf no official Corendon Airlines guidance exists for the specific scenario, evaluate only the agent's communication quality, troubleshooting process, information gathering, and escalation behavior. Do not invent or infer airline policies.\n\n\n## Related Policy Check\n\nWhen evaluating this conversation, verify whether the agent followed the official **Corendon Airlines Online Check-in policy and procedures**.\n\nCheck whether the agent:\n\n* Followed the official Corendon Airlines online check-in process.\n* Provided accurate information regarding online check-in eligibility, availability, and procedures.\n* Collected all required information before troubleshooting.\n* Performed all required troubleshooting steps before providing guidance.\n* Escalated the case when the issue required backend verification or technical support.\n* Avoided making unsupported assumptions or commitments.\n* Stayed within the permissions of their support level (L1/L2/L3).\n\nIf the agent's response contradicts the official Corendon Airlines Online Check-in policy or skips mandatory troubleshooting or escalation steps, record the appropriate QA finding according to the defined severity (Critical Error, Major Error, or Observation).\n\n",
    "perfectExample": "{\n  \"pet_id\": \"PET-1782715000000-CHECKIN01\",\n  \"customer_name\": \"Michael Anderson\",\n  \"issue\": \"Online Check-in Closed\",\n  \"qa_finding\": {\n    \"result\": \"QA Error Found\",\n    \"errors\": [\n      \"Misleading Information\"\n    ]\n  },\n  \"critical_chat_logs\": [\n    {\n      \"speaker\": \"Customer\",\n      \"name\": \"Michael Anderson\",\n      \"message\": \"I'm flying from Amsterdam to Antalya tomorrow. I tried to check in online, but it says online check-in is unavailable. Can you help?\"\n    },\n    {\n      \"speaker\": \"Agent\",\n      \"name\": \"Agent\",\n      \"message\": \"Could you please tell me how many hours remain before your flight departure?\"\n    },\n    {\n      \"speaker\": \"Customer\",\n      \"name\": \"Michael Anderson\",\n      \"message\": \"About 5 hours.\"\n    },\n    {\n      \"speaker\": \"Agent\",\n      \"name\": \"Agent\",\n      \"message\": \"Online check-in is already closed. Unfortunately, you can no longer check in for your flight.\"\n    },\n    {\n      \"speaker\": \"Customer\",\n      \"name\": \"Michael Anderson\",\n      \"message\": \"Does that mean I can't travel anymore?\"\n    },\n    {\n      \"speaker\": \"Agent\",\n      \"name\": \"Agent\",\n      \"message\": \"Yes. Since online check-in is closed, you have missed the check-in process and will need to purchase a new ticket.\"\n    }\n  ],\n  \"expected_agent_actions\": [\n    \"Verify the departure time.\",\n    \"Verify whether airport check-in is still available.\",\n    \"Inform the customer that online check-in and airport check-in are different.\",\n    \"Advise the customer to proceed to the airport check-in counter if it is still open.\",\n    \"Avoid assuming the passenger cannot travel without verifying airport check-in eligibility.\"\n  ],\n  \"agent_actions\": {\n    \"summary\": \"The agent assumed that because online check-in had closed, the customer was no longer allowed to travel and advised purchasing a new ticket.\"\n  },\n  \"missing_expected_actions\": [\n    \"Failed to distinguish between online check-in and airport check-in.\",\n    \"Failed to advise the customer to proceed to the airport check-in counter.\",\n    \"Failed to verify whether airport check-in was still open.\",\n    \"Incorrectly concluded that the customer had missed the flight.\"\n  ],\n  \"aht_delay_analysis\": {\n    \"result\": \"No AHT Issue\",\n    \"conversation_timeline\": [\n      {\n        \"observation\": \"All agent responses were within 2 minutes.\"\n      }\n    ],\n    \"threshold_minutes\": 4,\n    \"observation\": \"No response exceeded the 4-minute QA threshold.\"\n  },\n  \"reason\": \"Closing of online check-in does not automatically mean the passenger cannot travel. Airport check-in may still be available depending on the airline's check-in deadline. The agent incorrectly instructed the customer to purchase a new ticket without verifying whether airport check-in was still open, resulting in misleading guidance.\",\n  \"qa_conclusion\": {\n    \"status\": \"QA Failed\",\n    \"misleading\": true,\n    \"severity\": \"Major\",\n    \"qa_observations\": [\n      \"Incorrect check-in guidance.\",\n      \"Verification failure.\",\n      \"Wrong information provided.\",\n      \"Failed to advise airport check-in.\",\n      \"No escalation required.\",\n      \"No AHT issue.\"\n    ],\n    \"decision\": \"The agent provided misleading information by equating the closure of online check-in with the inability to travel. Proper verification of airport check-in availability was required before advising the customer to purchase a new ticket.\"\n  }\n}\n"
  },
  "Meal / Seat": {
    "globalInstructions": "# QA Knowledge Base – Category: Meal & Seat\n\n## QA Evaluation Scope\n\nEvaluate whether the support agent correctly handled **Meal, Seat, Severe Allergy, Onboard Wi-Fi, and related onboard service requests** according to Corendon Airlines' support procedures.\n\n**Important:** Evaluate only the **agent's actions**, not whether the customer ultimately received the requested service or compensation.\n\n---\n\n# Related Policy Check\n\nWhen evaluating this conversation, verify whether the agent followed the official **Corendon Airlines Meal & Seat policy and procedures**.\n\nCheck whether the agent:\n\n* Followed the correct Corendon Airlines process.\n* Collected all mandatory information before providing guidance.\n* Performed the required troubleshooting steps.\n* Stayed within the permissions of their support level (L1/L2/L3).\n* Escalated the case whenever required.\n* Avoided making unsupported commitments or promises.\n* Documented the case correctly in the CRM where applicable.\n\nIf the agent's response contradicts the official Corendon Airlines Meal & Seat policy or skips mandatory troubleshooting, verification, or escalation steps, record the appropriate QA finding according to the defined severity.\n\n---\n\n# 1. Severe Allergies\n\n## Expected Agent Actions\n\nTreat every allergy-related complaint as a **high-priority safety incident**.\n\nThe agent should:\n\n* Express empathy.\n* Collect:\n\n  * Booking reference\n  * Flight number\n  * Travel date\n  * Description of the allergy\n  * Food or beverage consumed\n  * Symptoms experienced\n  * Whether medical assistance was provided onboard or after landing\n  * Supporting medical documents (if available)\n* Document all collected information in the CRM.\n* Escalate immediately to **L3 Support** for review with the **In-Flight Services/Safety Team**.\n\n---\n\n## Agent Restrictions\n\nL1 and L2 agents must **not**:\n\n* Determine liability.\n* Admit fault.\n* Promise compensation.\n* Confirm reimbursement.\n* Decide the outcome of the complaint.\n\n---\n\n## Critical Error\n\nMark as a **Critical Error** if the agent:\n\n* Admits airline fault.\n* Accepts liability.\n* Promises compensation or reimbursement.\n* Closes the case without escalation.\n* Fails to treat the complaint as a safety-related incident.\n\n---\n\n# 2. Pre-Ordered Meal Discrepancies\n\n## Expected Agent Actions\n\nThe agent should collect:\n\n* Booking reference\n* Flight number\n* Travel date\n* Meal confirmation or payment receipt\n* Type of meal ordered\n\nDocument all supporting documents and customer comments in the CRM.\n\nEscalate the case to **L3 Support**.\n\nL3 will verify:\n\n* Meal booking status\n* Catering synchronization\n* System synchronization issues\n* Eligibility for reimbursement or goodwill compensation\n\n---\n\n## Agent Restrictions\n\nL1 and L2 agents must **not**:\n\n* Confirm the meal request was successfully processed.\n* Confirm catering errors.\n* Promise reimbursement.\n* Promise compensation.\n\n---\n\n## Critical Error\n\nMark as a **Critical Error** if the agent:\n\n* Confirms the meal booking without verification.\n* Promises reimbursement or compensation.\n* Gives a final resolution requiring backend verification.\n\n---\n\n# 3. Onboard Wi-Fi\n\n## Expected Agent Actions\n\nCollect:\n\n* Flight number\n* Travel date\n* Whether Wi-Fi was available\n* Purchase method (onboard or advance purchase)\n* Issue description\n* Proof of purchase\n\nProvide only basic troubleshooting:\n\n* Flight Mode enabled.\n* Wi-Fi enabled.\n* Connected to aircraft Wi-Fi.\n* Reconnect or restart device.\n\nIf unresolved or refund requested:\n\nEscalate to **L3 Support**.\n\nDocument the case in the CRM.\n\n---\n\n## Agent Restrictions\n\nL1 and L2 agents must **not**:\n\n* Verify Wi-Fi service logs.\n* Confirm technical failures.\n* Approve refunds.\n* Confirm refund eligibility.\n\n---\n\n## Critical Error\n\nMark as a **Critical Error** if the agent:\n\n* Promises a refund.\n* Confirms a technical outage without verification.\n* Guarantees reimbursement.\n* Provides a final resolution requiring backend verification.\n\n---\n\n# 4. Seat Issues / Seat Changes / Seat Requests\n\n## Expected Agent Actions\n\nThe agent should:\n\n* Listen empathetically to upset customers.\n* Collect all relevant booking and seat information.\n* Provide basic troubleshooting or guidance where applicable.\n* Advise customers to contact the onboard cabin crew for seat-related issues that can only be handled during the flight.\n* Escalate unresolved issues according to the support hierarchy.\n\nEscalation Flow:\n\n* **L1 → L2**\n* **L2 → L3**\n\nDocument the interaction in the CRM before escalation.\n\n---\n\n## Agent Restrictions\n\nL1 and L2 agents must **not**:\n\n* Guarantee a specific seat.\n* Promise an extra legroom seat.\n* Promise a seat upgrade.\n* Confirm seat allocation without verification.\n* Promise that a requested seat change will definitely occur.\n\n---\n\n## Critical Error\n\nMark as a **Critical Error** if the agent:\n\n* Guarantees any seat assignment.\n* Promises extra legroom seating.\n* Promises an upgrade.\n* Confirms seat allocation without authorization.\n* Gives any unsupported commitment regarding seating.\n\n---\n\n# QA Evaluation Criteria\n\nEvaluate whether the agent:\n\n* Collected all required information.\n* Performed the required troubleshooting.\n* Stayed within their authorized permissions.\n* Avoided unsupported commitments.\n* Escalated appropriately.\n* Documented the case correctly.\n* Followed the official Corendon Airlines Meal & Seat procedures.\n\n---\n\n# QA Decision Logic\n\n### PASS\n\nThe agent:\n\n* Followed the official process.\n* Gathered all required information.\n* Performed appropriate troubleshooting.\n* Escalated when required.\n* Stayed within their authority.\n\n### MAJOR ERROR\n\nThe agent:\n\n* Failed to collect mandatory information.\n* Skipped required troubleshooting.\n* Failed to escalate.\n* Provided incorrect procedural guidance.\n\n### CRITICAL ERROR\n\nThe agent:\n\n* Made any unsupported promise or commitment.\n* Confirmed backend information without verification.\n* Promised compensation, reimbursement, refunds, seat allocation, upgrades, or other outcomes beyond their authority.\n* Violated the official Corendon Airlines Meal & Seat policy.\n\n---\n\n# QA Principle\n\nAlways evaluate the **agent's adherence to Corendon Airlines' official Meal & Seat procedures**, not the final customer outcome.\n\nAny commitment, confirmation, approval, or assurance beyond the authority of the agent's support level must be recorded as a **Critical Error**.\n",
    "perfectExample": "{\n  \"pet_id\": \"PET-1782709449770-0ESBGQ88Q\",\n  \"customer_name\": \"Susan Herrera\",\n  \"issue\": \"Meal Pre-Order Deadline Inquiry\",\n  \"qa_finding\": {\n    \"result\": \"QA Error Found\",\n    \"errors\": [\n      \"Partial Resolution\",\n      \"Verification Failure\"\n    ]\n  },\n  \"critical_chat_logs\": [\n    {\n      \"speaker\": \"Customer\",\n      \"name\": \"Susan Herrera\",\n      \"message\": \"Yeah, actually. Can you please tell me the deadline to pre-order a meal for my flight, if I do that myself?\"\n    },\n    {\n      \"speaker\": \"Agent\",\n      \"name\": \"Emma\",\n      \"message\": \"Susan, for Corendon Airlines it's 72 hours before departure time, but as you have booked through a travel agency the best is to contact them so they can assist and help you to order pre-meal.\"\n    },\n    {\n      \"speaker\": \"Customer\",\n      \"name\": \"Susan Herrera\",\n      \"message\": \"Yeah, okay. So 72 hours before departure time is when I need to order my meal, if I do it myself. What time is that for my flight?\"\n    },\n    {\n      \"speaker\": \"Agent\",\n      \"name\": \"Emma\",\n      \"message\": \"I dont want to share any wrong information with you, as you booked with a third party; only they have the access to your booking and they will look into your booking to provide you the time for your flight and help you with booking your meal.\"\n    }\n  ],\n  \"expected_agent_actions\": [\n    \"Inform the customer that meal pre-orders must be completed 72 hours before scheduled departure.\",\n    \"Verify whether the customer has the flight departure date/time or booking reference.\",\n    \"If booking details are unavailable, advise the customer to check the itinerary or contact the travel agency.\",\n    \"Explain that chat support cannot access third-party bookings.\"\n  ],\n  \"agent_actions\": {\n    \"summary\": \"The agent correctly informed the customer that meal pre-orders close 72 hours before departure and correctly advised the customer to contact the travel agency because the booking was made through a third party. However, when the customer asked how to calculate the deadline for their own flight, the agent did not attempt to verify whether the customer had the itinerary or departure details available and instead repeatedly redirected the customer to the travel agency.\"\n  },\n  \"missing_expected_actions\": [\n    \"Failed to verify whether the customer had the flight itinerary or departure date/time available.\",\n    \"Missed the opportunity to guide the customer on calculating the 72-hour deadline if the departure time was known.\",\n    \"Repeated referral to the travel agency without attempting additional verification.\"\n  ],\n  \"aht_delay_analysis\": {\n    \"result\": \"No Major AHT Issue\",\n    \"conversation_timeline\": [\n      {\n        \"start\": \"10:36\",\n        \"end\": \"10:38\",\n        \"duration_minutes\": 2,\n        \"status\": \"Acceptable\"\n      },\n      {\n        \"start\": \"10:40\",\n        \"end\": \"10:42\",\n        \"duration_minutes\": 2,\n        \"status\": \"Acceptable\"\n      }\n    ],\n    \"threshold_minutes\": 4,\n    \"observation\": \"All remaining responses were within the acceptable QA response time.\"\n  },\n  \"reason\": \"The agent correctly explained the 72-hour meal pre-order policy but did not verify whether the customer had the flight itinerary or departure time available to calculate the deadline. Instead, the conversation repeatedly redirected the customer to the travel agency without attempting further guidance.\",\n  \"qa_conclusion\": {\n    \"status\": \"QA Failed\",\n    \"misleading\": false,\n    \"severity\": \"Non-Critical\",\n    \"qa_errors_identified\": [\n      \"Verification Failure\",\n      \"Partial Resolution\",\n      \"Missed guidance opportunity\"\n    ],\n    \"decision\": \"The information provided was accurate; however, the agent missed an opportunity to verify available flight details and better assist the customer in determining the meal pre-order deadline. This is classified as a Non-Critical Verification Failure.\"\n  }\n}"
  },
  "Other": {
    "globalInstructions": "# QA Knowledge Base – Category: Other (Loyalty, Airport Operations & General Escalation)\n\n## QA Evaluation Scope\n\nEvaluate whether the support agent correctly handled **Loyalty Programs, Membership, Promo Codes, Boarding Pass Scanning Issues, General Information Gathering, Escalation Standards, and other operational requests** according to Corendon Airlines' official procedures.\n\n> **Important:** Evaluate only the **agent's actions**, not the customer's eligibility or the final business outcome.\n\n---\n\n# Related Policy Check\n\nWhen evaluating a conversation in this category, verify whether the agent followed the official **Corendon Airlines policy** related to the customer's issue.\n\nCheck whether the agent:\n\n* Followed the correct Corendon Airlines procedure.\n* Collected all mandatory information before providing guidance.\n* Asked only relevant questions.\n* Performed all required troubleshooting within the L1/L2 scope.\n* Stayed within their authorized permissions.\n* Escalated the case when required.\n* Avoided unsupported commitments or promises.\n* Documented the case correctly in the CRM.\n\nIf the agent's response contradicts the official Corendon Airlines policy or skips mandatory verification, troubleshooting, or escalation steps, record the appropriate QA finding.\n\n---\n\n# 1. Membership, Loyalty Program & Promo Codes\n\n## Expected Agent Actions\n\nThe agent must first verify the **original booking source**.\n\nDetermine whether the booking was made:\n\n* Directly with Corendon Airlines (Website, Mobile App, Customer Service)\n* Through a Travel Agency\n* OTA (Online Travel Agency)\n* Tour Operator\n* Third-party Booking Partner\n\nIf the promotion or loyalty benefit belongs to a third-party booking partner, advise the customer to contact that booking provider.\n\nIf the booking was made directly with Corendon Airlines, collect:\n\n* Booking reference\n* Registered email address\n* Promo code (if applicable)\n* Screenshot of the error\n* Description of the issue\n\nDocument all supporting information before escalation.\n\n---\n\n## Agent Restrictions\n\nL1 and L2 agents must **not**:\n\n* Verify membership account status.\n* Verify promo code eligibility.\n* Verify campaign participation.\n* Verify discount application failures.\n* Apply promo codes manually.\n* Override discounts.\n* Promise eligibility.\n* Promise exceptions.\n\nEligible Corendon cases must be escalated to **L3 Support**.\n\n---\n\n## Critical Error\n\nMark as a **Critical Error** if the agent:\n\n* Applies or overrides promotional discounts.\n* Confirms campaign eligibility without verification.\n* Promises loyalty benefits.\n* Confirms promo code validity without verification.\n* Makes any unsupported commitment requiring L3 verification.\n\n---\n\n# 2. Boarding Pass Scanning Issues\n\n## Expected Agent Actions\n\nIf a customer reports that their boarding pass cannot be scanned at the boarding gate:\n\nThe agent should:\n\n* Collect the booking reference.\n* Collect the flight number.\n* Collect the travel date.\n* Understand the issue before escalation.\n* Provide only guidance that is within the L1/L2 support scope.\n\nIf remote resolution is not possible, escalate according to the official Corendon Airlines process.\n\n---\n\n## Agent Restrictions\n\nL1 and L2 agents must **not**:\n\n* Confirm the cause of the scanning failure without verification.\n* Promise boarding approval.\n* Override airport or gate decisions.\n* Promise that the issue will definitely be resolved.\n\n---\n\n## Critical Error\n\nMark as a **Critical Error** if the agent:\n\n* Confirms boarding eligibility without verification.\n* Overrides airport operational decisions.\n* Makes unsupported commitments regarding boarding.\n\n---\n\n# 3. Mandatory Information Gathering\n\nBefore escalating any case, the agent must:\n\n* Clearly understand the customer's issue.\n* Ask only relevant and case-specific questions.\n* Verify all available information within the L1/L2 scope.\n* Collect all mandatory information based on the issue type.\n* Record a complete and accurate summary in the CRM.\n\nExamples of mandatory information include:\n\n* Booking reference\n* Passenger name\n* Flight number\n* Travel date\n* Issue-specific supporting information\n\n---\n\n## Critical Compliance\n\nThe agent must **not** request unnecessary or irrelevant information.\n\nIf an agent requests information that is not required for investigating or resolving the reported issue, this should be marked as a **Critical Error**, as it increases customer effort, delays resolution, and negatively impacts the customer experience.\n\n---\n\n# 4. Escalation Standard\n\nA case should only be escalated after:\n\n* The customer's actual issue has been clearly identified.\n* All mandatory information has been collected.\n* Supporting documents or information have been obtained where applicable.\n* CRM notes contain a complete and accurate summary.\n* The agent has confirmed that the issue cannot be resolved within the L1/L2 scope.\n\nEscalation Flow:\n\n* **L1 → L2**\n* **L2 → L3**\n\nOnly **L3** may perform backend verification or provide final decisions requiring system access or policy validation.\n\n---\n\n## QA Evaluation Criteria\n\nEvaluate whether the agent:\n\n* Understood the customer's issue.\n* Asked only relevant questions.\n* Collected all mandatory information.\n* Followed the official Corendon Airlines procedure.\n* Stayed within their authorized permissions.\n* Avoided unsupported commitments.\n* Escalated appropriately.\n* Documented the case correctly in the CRM.\n\n---\n\n# QA Decision Logic\n\n### PASS\n\nThe agent:\n\n* Followed the correct process.\n* Collected all required information.\n* Asked relevant questions only.\n* Escalated appropriately.\n* Stayed within their authority.\n\n### MAJOR ERROR\n\nThe agent:\n\n* Failed to collect mandatory information.\n* Skipped required troubleshooting.\n* Failed to follow the official process.\n* Failed to escalate when required.\n* Provided incorrect procedural guidance.\n\n### CRITICAL ERROR\n\nThe agent:\n\n* Requested unnecessary or irrelevant information.\n* Made unsupported commitments or promises.\n* Confirmed backend information without verification.\n* Applied or approved loyalty benefits without authorization.\n* Promised discounts, promotions, or boarding outcomes beyond their authority.\n* Violated the official Corendon Airlines policy for the related issue.\n\n---\n\n# QA Principle\n\nAlways evaluate the **agent's adherence to the official Corendon Airlines procedures**, not the final customer outcome.\n\nAny commitment, confirmation, approval, assurance, or resolution beyond the authority of the agent's support level must be recorded as a **Critical Error**.\n"
  }
}